nmeatoolkit/__init__.py
nmeatoolkit/args.py
nmeatoolkit/pipeline.py
nmeatoolkit/pipes/__init__.py
nmeatoolkit/pipes/crop.py
nmeatoolkit/pipes/filter.py
nmeatoolkit/pipes/pipe.py
nmeatoolkit/pipes/seatalk.py
nmeatoolkit/pipes/truewind.py
nmeatoolkit/streams/__init__.py
nmeatoolkit/streams/inputs.py
nmeatoolkit/streams/outputs.py
nmeatoolkit/translators/__init__.py
nmeatoolkit/translators/gpx.py
nmeatoolkit/translators/identity.py
nmeatoolkit/translators/polar.py
nmeatoolkit/translators/tostring.py
nmeatoolkit/translators/trackpoint.py
nmeatoolkit/translators/translator.py
nmeatoolkit-0.2.dist-info/licenses/LICENSE
tools/__init__.py
tools/nmea2gpx.py
tools/nmea2polar.py
tools/nmeatk.py
tools/stalk2nmea.py
nmeatoolkit-0.2.dist-info/METADATA
nmeatoolkit-0.2.dist-info/WHEEL
nmeatoolkit-0.2.dist-info/entry_points.txt
nmeatoolkit-0.2.dist-info/top_level.txt
nmeatoolkit-0.2.dist-info/RECORD
